beancount_mercury/__init__.py
beancount_mercury/checking.py
beancount_mercury/checking_test.py
beancount_mercury-0.1.4.dist-info/LICENSE
beancount_mercury-0.1.4.dist-info/METADATA
beancount_mercury-0.1.4.dist-info/WHEEL
beancount_mercury-0.1.4.dist-info/top_level.txt
beancount_mercury-0.1.4.dist-info/RECORD
