Metadata-Version: 2.1
Name: beancount-mercury
Version: 0.1.4
Summary: Import Mercury banking transactions into beancount format
Home-page: https://github.com/mtlynch/beancount-mercury.git
Author: Michael Lynch
License: MIT
Keywords: mercury beancount bookkeeping finance
Platform: UNKNOWN
Requires-Python: >=3.9
Requires-Dist: beancount (>=2.3.0)
Requires-Dist: titlecase (>=2.0.0)
